README.md
setup.py
xmind/__init__.py
xmind/utils.py
xmind/core/__init__.py
xmind/core/const.py
xmind/core/loader.py
xmind/core/markerref.py
xmind/core/mixin.py
xmind/core/notes.py
xmind/core/position.py
xmind/core/relationship.py
xmind/core/saver.py
xmind/core/sheet.py
xmind/core/title.py
xmind/core/topic.py
xmind/core/workbook.py
xmind/tests/__init__.py
xmind/tests/base.py
xmind/tests/create_xmind_file_from_json.py
xmind/tests/logging_configuration.py
xmind/tests/test_compare_xmind_file_with_etalon.py
xmind/tests/test_const.py
xmind/tests/test_document.py
xmind/tests/test_e2e_open.py
xmind/tests/test_element.py
xmind/tests/test_loader.py
xmind/tests/test_markerref_markerid.py
xmind/tests/test_markerref_markerrefselement.py
xmind/tests/test_markerrefelement.py
xmind/tests/test_node.py
xmind/tests/test_notes_element.py
xmind/tests/test_notes_note_content_element.py
xmind/tests/test_notes_plain_notes.py
xmind/tests/test_position.py
xmind/tests/test_relationship_element.py
xmind/tests/test_relationships_element.py
xmind/tests/test_sheet_element.py
xmind/tests/test_title_element.py
xmind/tests/test_topic_children_element.py
xmind/tests/test_topic_element.py
xmind/tests/test_topic_mixin_element.py
xmind/tests/test_topics_element.py
xmind/tests/test_utils.py
xmind/tests/test_workbook_document.py
xmind/tests/test_workbook_element.py
xmind/tests/test_workbook_mixin_element.py
xmind/tests/test_workbook_saver.py
xmind/tests/test_xmind__init__.py
xmind_sdk_python_upload_file.egg-info/PKG-INFO
xmind_sdk_python_upload_file.egg-info/SOURCES.txt
xmind_sdk_python_upload_file.egg-info/dependency_links.txt
xmind_sdk_python_upload_file.egg-info/top_level.txt