Metadata-Version: 1.2
Name: xmind-sdk-python-upload-file
Version: 1.0
Summary: The offical XMind python SDK
Home-page: https://github.com/xqlip/xmind-sdk-python.git
Author: qinglin
Author-email: 1148865821@qq.com
License: MIT
Download-URL: https://github.com/xqlip/xmind-sdk-python/archive/v1.1.tar.gz
Keywords: XMind,SDK,mind mapping
Platform: UNKNOWN
Classifier: Programming Language :: Python :: 3
Classifier: License :: OSI Approved :: MIT License
Classifier: Operating System :: OS Independent
Requires-Python: >=3.6
